CHANGES.txt
LICENSE.txt
MANIFEST.in
README.txt
buildout.cfg
setup.py
.eggs/README.txt
eggs/future-1.0.0-py3.10.egg/EGG-INFO/LICENSE.txt
eggs/future-1.0.0-py3.10.egg/EGG-INFO/entry_points.txt
eggs/future-1.0.0-py3.10.egg/EGG-INFO/top_level.txt
eggs/lovely.recipe-1.0.0-py3.10.egg/EGG-INFO/SOURCES.txt
eggs/lovely.recipe-1.0.0-py3.10.egg/EGG-INFO/dependency_links.txt
eggs/lovely.recipe-1.0.0-py3.10.egg/EGG-INFO/entry_points.txt
eggs/lovely.recipe-1.0.0-py3.10.egg/EGG-INFO/namespace_packages.txt
eggs/lovely.recipe-1.0.0-py3.10.egg/EGG-INFO/requires.txt
eggs/lovely.recipe-1.0.0-py3.10.egg/EGG-INFO/top_level.txt
eggs/lovely.recipe-1.0.0-py3.10.egg/lovely/recipe/egg/README.txt
eggs/lovely.recipe-1.0.0-py3.10.egg/lovely/recipe/fs/README.txt
eggs/lovely.recipe-1.0.0-py3.10.egg/lovely/recipe/fs/mkdir-root.txt
eggs/lovely.recipe-1.0.0-py3.10.egg/lovely/recipe/i18n/README.txt
eggs/lovely.recipe-1.0.0-py3.10.egg/lovely/recipe/importchecker/README.txt
eggs/m01.fake-3.13.2-py3.10.egg/EGG-INFO/SOURCES.txt
eggs/m01.fake-3.13.2-py3.10.egg/EGG-INFO/dependency_links.txt
eggs/m01.fake-3.13.2-py3.10.egg/EGG-INFO/namespace_packages.txt
eggs/m01.fake-3.13.2-py3.10.egg/EGG-INFO/requires.txt
eggs/m01.fake-3.13.2-py3.10.egg/EGG-INFO/top_level.txt
eggs/m01.fake-3.13.2-py3.10.egg/m01/fake/README.txt
eggs/m01.fake-3.13.2-py3.10.egg/m01/fake/client.txt
eggs/m01.fake-3.13.2-py3.10.egg/m01/fake/collection-find.txt
eggs/m01.fake-3.13.2-py3.10.egg/m01/fake/collection-update.txt
eggs/m01.fake-3.13.2-py3.10.egg/m01/fake/collection.txt
eggs/m01.fake-3.13.2-py3.10.egg/m01/fake/database.txt
eggs/m01.fake-3.13.2-py3.10.egg/m01/fake/finder.txt
eggs/m01.fake-3.13.2-py3.10.egg/m01/fake/index.txt
eggs/m01.fake-3.13.2-py3.10.egg/m01/fake/testing.txt
eggs/m01.fake-3.13.2-py3.10.egg/m01/fake/sandbox/LICENSE-Community.txt
eggs/m01.fake-3.13.3-py3.10.egg/EGG-INFO/SOURCES.txt
eggs/m01.fake-3.13.3-py3.10.egg/EGG-INFO/dependency_links.txt
eggs/m01.fake-3.13.3-py3.10.egg/EGG-INFO/namespace_packages.txt
eggs/m01.fake-3.13.3-py3.10.egg/EGG-INFO/requires.txt
eggs/m01.fake-3.13.3-py3.10.egg/EGG-INFO/top_level.txt
eggs/m01.fake-3.13.3-py3.10.egg/m01/fake/README.txt
eggs/m01.fake-3.13.3-py3.10.egg/m01/fake/client.txt
eggs/m01.fake-3.13.3-py3.10.egg/m01/fake/collection-find.txt
eggs/m01.fake-3.13.3-py3.10.egg/m01/fake/collection-update.txt
eggs/m01.fake-3.13.3-py3.10.egg/m01/fake/collection.txt
eggs/m01.fake-3.13.3-py3.10.egg/m01/fake/database.txt
eggs/m01.fake-3.13.3-py3.10.egg/m01/fake/finder.txt
eggs/m01.fake-3.13.3-py3.10.egg/m01/fake/index.txt
eggs/m01.fake-3.13.3-py3.10.egg/m01/fake/testing.txt
eggs/m01.fake-3.13.3-py3.10.egg/m01/fake/sandbox/LICENSE-Community.txt
eggs/pymongo-3.13.0-py3.10-win-amd64.egg/EGG-INFO/requires.txt
eggs/pymongo-3.13.0-py3.10-win-amd64.egg/EGG-INFO/top_level.txt
eggs/sentinels-1.0.0-py3.10.egg/EGG-INFO/SOURCES.txt
eggs/sentinels-1.0.0-py3.10.egg/EGG-INFO/dependency_links.txt
eggs/sentinels-1.0.0-py3.10.egg/EGG-INFO/namespace_packages.txt
eggs/sentinels-1.0.0-py3.10.egg/EGG-INFO/top_level.txt
eggs/six-1.17.0-py3.10.egg/EGG-INFO/top_level.txt
eggs/zc.recipe.egg-2.0.7-py3.10.egg/EGG-INFO/SOURCES.txt
eggs/zc.recipe.egg-2.0.7-py3.10.egg/EGG-INFO/dependency_links.txt
eggs/zc.recipe.egg-2.0.7-py3.10.egg/EGG-INFO/entry_points.txt
eggs/zc.recipe.egg-2.0.7-py3.10.egg/EGG-INFO/namespace_packages.txt
eggs/zc.recipe.egg-2.0.7-py3.10.egg/EGG-INFO/requires.txt
eggs/zc.recipe.egg-2.0.7-py3.10.egg/EGG-INFO/top_level.txt
eggs/zc.recipe.testrunner-3.2-py3.10.egg/EGG-INFO/LICENSE.txt
eggs/zc.recipe.testrunner-3.2-py3.10.egg/EGG-INFO/entry_points.txt
eggs/zc.recipe.testrunner-3.2-py3.10.egg/EGG-INFO/namespace_packages.txt
eggs/zc.recipe.testrunner-3.2-py3.10.egg/EGG-INFO/requires.txt
eggs/zc.recipe.testrunner-3.2-py3.10.egg/EGG-INFO/top_level.txt
eggs/zope.exceptions-5.2-py3.10.egg/EGG-INFO/LICENSE.txt
eggs/zope.exceptions-5.2-py3.10.egg/EGG-INFO/namespace_packages.txt
eggs/zope.exceptions-5.2-py3.10.egg/EGG-INFO/requires.txt
eggs/zope.exceptions-5.2-py3.10.egg/EGG-INFO/top_level.txt
eggs/zope.interface-7.2-py3.10-win-amd64.egg/EGG-INFO/LICENSE.txt
eggs/zope.interface-7.2-py3.10-win-amd64.egg/EGG-INFO/namespace_packages.txt
eggs/zope.interface-7.2-py3.10-win-amd64.egg/EGG-INFO/requires.txt
eggs/zope.interface-7.2-py3.10-win-amd64.egg/EGG-INFO/top_level.txt
eggs/zope.testing-5.1-py3.10.egg/EGG-INFO/LICENSE.txt
eggs/zope.testing-5.1-py3.10.egg/EGG-INFO/namespace_packages.txt
eggs/zope.testing-5.1-py3.10.egg/EGG-INFO/requires.txt
eggs/zope.testing-5.1-py3.10.egg/EGG-INFO/top_level.txt
eggs/zope.testing-5.1-py3.10.egg/zope/testing/cleanup.txt
eggs/zope.testing-5.1-py3.10.egg/zope/testing/doctestcase.txt
eggs/zope.testing-5.1-py3.10.egg/zope/testing/formparser.txt
eggs/zope.testing-5.1-py3.10.egg/zope/testing/loggingsupport.txt
eggs/zope.testing-5.1-py3.10.egg/zope/testing/module.txt
eggs/zope.testing-5.1-py3.10.egg/zope/testing/renormalizing.txt
eggs/zope.testing-5.1-py3.10.egg/zope/testing/setupstack.txt
eggs/zope.testrunner-7.4-py3.10.egg/EGG-INFO/entry_points.txt
eggs/zope.testrunner-7.4-py3.10.egg/EGG-INFO/namespace_packages.txt
eggs/zope.testrunner-7.4-py3.10.egg/EGG-INFO/requires.txt
eggs/zope.testrunner-7.4-py3.10.egg/EGG-INFO/top_level.txt
src/m01.stub.egg-info/PKG-INFO
src/m01.stub.egg-info/SOURCES.txt
src/m01.stub.egg-info/dependency_links.txt
src/m01.stub.egg-info/namespace_packages.txt
src/m01.stub.egg-info/not-zip-safe
src/m01.stub.egg-info/requires.txt
src/m01.stub.egg-info/top_level.txt
